best/__init__.py
best/integration/__init__.py
best/unit/__init__.py
best/unit/conftest.py
best/unit/test_glue_session.py
best/unit/test_glue_session_demo.py
best/unit/test_session_apis.py
py_lief-0.9.0.dist-info/LICENSE.txt
py_lief-0.9.0.dist-info/METADATA
py_lief-0.9.0.dist-info/WHEEL
py_lief-0.9.0.dist-info/top_level.txt
py_lief-0.9.0.dist-info/RECORD
