Metadata-Version: 2.1
Name: py-lief
Version: 0.9.0
Summary: py-lief of py-lief of py-lief
Home-page: UNKNOWN
Author: Aloneee walker
Author-email: aloneewalker@facebook.com
License: UNKNOWN
Platform: UNKNOWN
Classifier: Programming Language :: Python :: 3
Classifier: License :: OSI Approved :: MIT License
Classifier: Operating System :: OS Independent
